tissuebox/__init__.py
tissuebox/basic.py
tissuebox/helpers.py
tissuebox-2025.1.3.dist-info/METADATA
tissuebox-2025.1.3.dist-info/WHEEL
tissuebox-2025.1.3.dist-info/top_level.txt
tissuebox-2025.1.3.dist-info/RECORD
