Metadata-Version: 2.1
Name: tissuebox
Version: 2025.1.3
Summary: Tissuebox :: Pythonic payload validator
Home-page: https://github.com/nehemiahjacob/tissuebox.git
Author: nehemiah
Author-email: nehemiah.jacob@gmail.com
